{
    "code": 200,
    "data": {
        "bookCount": 16,
        "bookIds": "1201,1202,1203,1204,1205,1206,1207,1168,1209,1210,1211,1212,327,1214,93,1216",
        "books": [
            {
                "authors": [
                    {
                        "firstName": "Joan",
                        "id": 1180,
                        "lastName": "Holub"
                    }
                ],
                "closeRead": false,
                "commoncores": null,
                "features": [                   
                    {
                        "code": "activities",
                        "id": 1,
                        "name": "Activities"
                    },
                    {
                        "code": "read-to-me",
                        "id": 3,
                        "name": "Read-to-Me"
                    }
                ],
                "id": 1207,
                "illustrators": [
                    {
                        "firstName": "Jan",
                        "id": 347,
                        "lastName": "Smith"
                    }
                ],
                "isbn": "9780545733472",
                "key": "$$*$$",
                "level": "L",
                "levelType": "Guided Reading Level",
                "shared": false,
                "shareType": null,
                "synopsis": "Using a field trip to an apple orchard as the setting, the author counts backward from 20 to 1. In addition to counting, the text includes simple addition, seasons of the year, and both number words and numerals.",
                "tipCard": true,
                "title": "Apple Countdown",
                "vbid": "$$*$$"
            },
            {
                "authors": [
                    {
                        "firstName": "Brian",
                        "id": 917,
                        "lastName": "Sargent"
                    }
                ],
                "closeRead": false,
                "commoncores": null,
                "features": null,
                "id": 1204,
                "illustrators": null,
                "isbn": "9780545705875",
                "key": "$$*$$",
                "level": "H",
                "levelType": "Guided Reading Level",
                "shared": false,
                "shareType": null,
                "synopsis": "It’s 7:00 a.m. and the birthday party starts at 12:00 noon. Before the party, a girl will need to get dressed, attend soccer practice, bake a cake, bike to a swim lesson, and wrap the present. The duration of each activity is highlighted as readers learn the concept of time as they follow her through her morning. Actions taking seconds, minutes and hours are featured.",
                "tipCard": false,
                "title": "A Busy Day (Rookie Read-About™ Math)",
                "vbid": "$$*$$"
            },
            {
                "authors": null,
                "closeRead": false,
                "commoncores": null,
                "features": null,
                "id": 1212,
                "illustrators": null,
                "isbn": "9780545739610",
                "key": "$$*$$",
                "level": "H",
                "levelType": "Guided Reading Level",
                "shared": false,
                "shareType": null,
                "synopsis": "This text helps readers count from one to five cougars, dolphins, zebras, macaws, and frogs while also learning unusual facts about these animals. At the end of the book, readers are encouraged to count to ten and then to twenty.",
                "tipCard": false,
                "title": "Count! (National Geographic Kids)",
                "vbid": "$$*$$"
            },
            {
                "authors": null,
                "closeRead": false,
                "commoncores": null,
                "features": [
                    {
                        "code": "read-to-me",
                        "id": 3,
                        "name": "Read-to-Me"
                    }
                ],
                "id": 1211,
                "illustrators": null,
                "isbn": "9780545739030",
                "key": "$$*$$",
                "level": "E",
                "levelType": "Guided Reading Level",
                "shared": false,
                "shareType": null,
                "synopsis": "As children learn numerals and number words, they can practice counting colorful, familiar objects on each page. This book even challenges readers to count backwards from ten to one.",
                "tipCard": false,
                "title": "Counting 1 to 10 (Rookie Toddler™)",
                "vbid": "$$*$$"
            },
            {
                "authors": [
                    {
                        "firstName": "",
                        "id": 3,
                        "lastName": "Scholastic"
                    }
                ],
                "closeRead": false,
                "commoncores": null,
                "features": null,
                "id": 1202,
                "illustrators": null,
                "isbn": "9780545694360",
                "key": "$$*$$",
                "level": "E",
                "levelType": "Guided Reading Level",
                "shared": false,
                "shareType": null,
                "synopsis": "Readers will meet frogs and kittens and even hedgehogs in this introduction to counting. Beginning with one ape then two sheep, three dogs, four horses and so forth, readers are presented with a new animal for every number as they learn to count to twenty.",
                "tipCard": false,
                "title": "Counting 1 to 20 (Rookie Toddler™)",
                "vbid": "$$*$$"
            },
            {
                "authors": [
                    {
                        "firstName": "",
                        "id": 3,
                        "lastName": "Scholastic"
                    }
                ],
                "closeRead": false,
                "commoncores": null,
                "features": null,
                "id": 1201,
                "illustrators": null,
                "isbn": "9780545694285",
                "key": "$$*$$",
                "level": "D",
                "levelType": "Guided Reading Level",
                "shared": false,
                "shareType": null,
                "synopsis": "Students count from one to ten using tools such as tape measures and levels. Clear photos accompany each numeral, number word, and tool name.",
                "tipCard": false,
                "title": "Counting Tools 1 to 10 (Rookie Toddler™)",
                "vbid": "$$*$$"
            },
            {
                "authors": [
                    {
                        "firstName": "Jerry",
                        "id": 44,
                        "lastName": "Pallotta"
                    },
                    {
                        "firstName": "Pam Munoz",
                        "id": 786,
                        "lastName": "Ryan"
                    }
                ],
                "closeRead": false,
                "commoncores": null,
                "features": null,
                "id": 1209,
                "illustrators": [
                    {
                        "firstName": "Frank",
                        "id": 288,
                        "lastName": "Mazzola Jr."
                    }
                ],
                "isbn": "9780545737050",
                "key": "$$*$$",
                "level": "L",
                "levelType": "Guided Reading Level",
                "shared": false,
                "shareType": null,
                "synopsis": "This book, written in rhyme, first teaches counting by twos using even numbers and then odd numbers. Readers will also learn color names and number words that correspond with the numerals.",
                "tipCard": false,
                "title": "The Crayon Counting Book",
                "vbid": "$$*$$"
            },
            {
                "authors": [
                    {
                        "firstName": "Steve",
                        "id": 296,
                        "lastName": "Metzger"
                    }
                ],
                "closeRead": false,
                "commoncores": null,
                "features": null,
                "id": 1214,
                "illustrators": [
                    {
                        "firstName": "Laura J.",
                        "id": 34,
                        "lastName": "Bryant"
                    }
                ],
                "isbn": "9780545744133",
                "key": "$$*$$",
                "level": "J",
                "levelType": "Guided Reading Level",
                "shared": false,
                "shareType": null,
                "synopsis": "With this rhyming story, children can count down from five to one as, one-by-one, five high-spirited little bats have near mishaps and disappear. When the last little bat disappears, the doctor tells the mother to let the little bats fly, and all five little bats reappear and fly in the night sky!",
                "tipCard": false,
                "title": "Five Little Bats Flying In The Night",
                "vbid": "$$*$$"
            },
            {
                "authors": [
                    {
                        "firstName": "Steve",
                        "id": 296,
                        "lastName": "Metzger"
                    }
                ],
                "closeRead": false,
                "commoncores": null,
                "features": [
                    {
                        "code": "read-to-me",
                        "id": 3,
                        "name": "Read-to-Me"
                    }
                ],
                "id": 327,
                "illustrators": [
                    {
                        "firstName": "Laura J.",
                        "id": 34,
                        "lastName": "Bryant"
                    }
                ],
                "isbn": "9780545743211",
                "key": "$$*$$",
                "level": "F",
                "levelType": "Guided Reading Level",
                "shared": false,
                "shareType": null,
                "synopsis": "With this rhyming story, children can count down from five to one as, one-by-one, five fun-loving little penguins have mishaps, prompting the mother penguin to call the doctor. The doctor tells the mother to stop the penguins from doing each activity. When there are no little penguins having any fun, the mother calls the doctor again. The doctor then says, \"Let those penguins have some fun!\" The five little penguins along with their mother are free to go outside and have some fun.",
                "tipCard": true,
                "title": "Five Little Penguins Slipping On The Ice",
                "vbid": "$$*$$"
            },
            {
                "authors": [
                    {
                        "firstName": "Jerry",
                        "id": 44,
                        "lastName": "Pallotta"
                    }
                ],
                "closeRead": false,
                "commoncores": null,
                "features": null,
                "id": 93,
                "illustrators": null,
                "isbn": "9780545744621",
                "key": "$$*$$",
                "level": "M",
                "levelType": "Guided Reading Level",
                "shared": false,
                "shareType": null,
                "synopsis": "Children practice their counting, addition, and subtraction by identifying bugs and their individual parts.  Colorful insect illustrations of beetles, ladybugs, dragonflies, and more, help readers learn to add by ones, twos, and tens.",
                "tipCard": true,
                "title": "Icky Bug Numbers",
                "vbid": "$$*$$"
            },
            {
                "authors": [
                    {
                        "firstName": "Jane",
                        "id": 1188,
                        "lastName": "Campbell"
                    }
                ],
                "closeRead": false,
                "commoncores": null,
                "features": null,
                "id": 1216,
                "illustrators": [
                    {
                        "firstName": "Clare",
                        "id": 352,
                        "lastName": "Watson"
                    }
                ],
                "isbn": "9780545765725",
                "key": "$$*$$",
                "level": "C",
                "levelType": "Guided Reading Level",
                "shared": false,
                "shareType": null,
                "synopsis": "Alex is ready to go on vacation, but it is only 3:00. She returns to wake her parents again at 4:00 and at 5:00. When it is time to go, Alex is fast asleep.",
                "tipCard": false,
                "title": "Is It Time?",
                "vbid": "$$*$$"
            },
            {
                "authors": [
                    {
                        "firstName": "",
                        "id": 3,
                        "lastName": "Scholastic"
                    }
                ],
                "closeRead": false,
                "commoncores": null,
                "features": [                   
                    {
                        "code": "activities",
                        "id": 1,
                        "name": "Activities"
                    },
                    {
                        "code": "read-to-me",
                        "id": 3,
                        "name": "Read-to-Me"
                    }
                ],
                "id": 1203,
                "illustrators": null,
                "isbn": "9780545694407",
                "key": "$$*$$",
                "level": "F",
                "levelType": "Guided Reading Level",
                "shared": false,
                "shareType": null,
                "synopsis": "Mornings are for breakfast and school, afternoons are for lunch and play, evenings are for dinner and brushing your teeth and night is for sleeping. Children learn to differentiate the parts of their day through association of these common activities. Analogue and digital clocks accompany each activity and help reinforce the timeline.",
                "tipCard": false,
                "title": "It Is Time For... (Rookie Toddler™)",
                "vbid": "$$*$$"
            },
            {
                "authors": [
                    {
                        "firstName": "Julie",
                        "id": 1178,
                        "lastName": "Dalton"
                    }
                ],
                "closeRead": false,
                "commoncores": null,
                "features": null,
                "id": 1205,
                "illustrators": null,
                "isbn": "9780545706384",
                "key": "$$*$$",
                "level": "H",
                "levelType": "Guided Reading Level",
                "shared": false,
                "shareType": null,
                "synopsis": "The world is filled with things to count. Children challenge their skill with numbers by counting fingers, animals, marbles, and hats, with the ultimate challenge being 136 pairs of eyeglasses.",
                "tipCard": false,
                "title": "Look and Count (Rookie Read-About™ Math)",
                "vbid": "$$*$$"
            },
            {
                "authors": [
                    {
                        "firstName": "Larry Dane",
                        "id": 1179,
                        "lastName": "Brimner"
                    }
                ],
                "closeRead": false,
                "commoncores": null,
                "features": null,
                "id": 1206,
                "illustrators": null,
                "isbn": "9780545707831",
                "key": "$$*$$",
                "level": "G",
                "levelType": "Guided Reading Level",
                "shared": false,
                "shareType": null,
                "synopsis": "Monkeys have invaded a house. They are looking around the sofa, under a lampshade and all around the kitchen, but the little boy has no idea what they lost until he finds their parents asleep in his room. Playful illustrations and a cute story make counting to twelve engaging and fun.",
                "tipCard": true,
                "title": "Monkey Math (A Rookie Reader™)",
                "vbid": "$$*$$"
            },
            {
                "authors": [
                    {
                        "firstName": "Chloe",
                        "id": 55,
                        "lastName": "Ryder"
                    }
                ],
                "closeRead": false,
                "commoncores": null,
                "features": null,
                "id": 1168,
                "illustrators": null,
                "isbn": "9780545735858",
                "key": "$$*$$",
                "level": "P",
                "levelType": "Guided Reading Level",
                "shared": false,
                "shareType": null,
                "synopsis": "Readers practice counting from one to ten (and down from ten to one) while exploring coral reefs, warm and sunny seas, sparkling ice packs, and other special spots where marine animals live and play. The sea creatures featured are the green sea turtle, harp seal, star-eye parrot fish, reef squid, pink sea star, Adelie penguin, glass eye fish, sea otter, hammerhead shark, and Bermuda sea chub. Each page includes a colorful photograph and facts of the featured ocean life and habitat. At the end of the book is a world map from which readers count the oceans, facts cards, a glossary, and a list of resources for more information.",
                "tipCard": true,
                "title": "Ocean Counting (National Geographic Kids)",
                "vbid": "$$*$$"
            },
            {
                "authors": [
                    {
                        "firstName": "Barbara Barbieri",
                        "id": 295,
                        "lastName": "McGrath"
                    }
                ],
                "closeRead": false,
                "commoncores": null,
                "features": [
                    {
                        "code": "read-to-me",
                        "id": 3,
                        "name": "Read-to-Me"
                    }
                ],
                "id": 1210,
                "illustrators": [
                    {
                        "firstName": "Tim",
                        "id": 33,
                        "lastName": "Nihoff"
                    }
                ],
                "isbn": "9780545737265",
                "key": "$$*$$",
                "level": "J",
                "levelType": "Guided Reading Level",
                "shared": false,
                "shareType": null,
                "synopsis": "This book ingeniously uses colored teddy bears and rhyming text to help children learn about several math concepts, including patterns, addition, subtraction, fractions, and counting. Children are asked, for example, to compare sets of blue, red, and yellow teddy bears and determine which set has the most.",
                "tipCard": false,
                "title": "Teddy Bear, Teddy Bear, School Day Math",
                "vbid": "$$*$$"
            }
        ],
        "description": "A robust skill-building set with basic counting books plus entertaining stories that contain simple math practice.",
        "grade": "Pre K",
        "iconCode": "&#xe62a;",
        "iconColor": "8031a7",
        "id": "28",
        "levelHigh": "P",
        "levelLow": "C",
        "name": "We Can Count",
        "recommend": "Independent Reading",
        "shared": true,
        "shareType": "students",
        "shareWith": [
            {
                "iconCode": null,
                "iconColor": null,
                "iconName": null,
                "id": 946,
                "name": "Ashish"
            },
            {
                "iconCode": null,
                "iconColor": null,
                "iconName": null,
                "id": 947,
                "name": "Sagar"
            }
        ],
        "type": "collection"
    },
    "errors": [],
    "message": "OK",
    "metaData": null
}